rdflib_orm/__init__.py
rdflib_orm/fields.py
rdflib_orm/models.py
rdflib_orm/db/__init__.py
tests/__init__.py
tests/test_database_class.py
tests/test_sparql_store_headers.py
tests/fields/__init__.py
tests/fields/test_charfield.py
tests/fields/test_irifield.py
rdflib_orm-0.2.1.dist-info/METADATA
rdflib_orm-0.2.1.dist-info/WHEEL
rdflib_orm-0.2.1.dist-info/top_level.txt
rdflib_orm-0.2.1.dist-info/RECORD
